crml_lang/__init__.py
crml_lang/__main__.py
crml_lang/api.py
crml_lang/cli.py
crml_lang/yamlio.py
crml_lang/bundling/__init__.py
crml_lang/bundling/portfolio_bundler.py
crml_lang/integrations/oscal/__init__.py
crml_lang/integrations/oscal/_require.py
crml_lang/integrations/oscal/catalog_ingest.py
crml_lang/integrations/oscal/ids.py
crml_lang/mapping/__init__.py
crml_lang/mapping/__main__.py
crml_lang/mapping/xlsx.py
crml_lang/models/__init__.py
crml_lang/models/assessment_model.py
crml_lang/models/attack_catalog_model.py
crml_lang/models/attack_control_relationships_model.py
crml_lang/models/control_catalog_model.py
crml_lang/models/control_ref.py
crml_lang/models/control_relationships_model.py
crml_lang/models/coverage_model.py
crml_lang/models/numberish.py
crml_lang/models/portfolio_bundle.py
crml_lang/models/portfolio_model.py
crml_lang/models/scenario_model.py
crml_lang/models/simulation_result.py
crml_lang/schemas/__init__.py
crml_lang/schemas/crml-assessment-schema.json
crml_lang/schemas/crml-attack-catalog-schema.json
crml_lang/schemas/crml-attack-control-relationships-schema.json
crml_lang/schemas/crml-control-catalog-schema.json
crml_lang/schemas/crml-control-relationships-schema.json
crml_lang/schemas/crml-portfolio-bundle-schema.json
crml_lang/schemas/crml-portfolio-schema.json
crml_lang/schemas/crml-scenario-schema.json
crml_lang/schemas/crml-simulation-result-schema.json
crml_lang/validators/__init__.py
crml_lang/validators/assessment.py
crml_lang/validators/attack_catalog.py
crml_lang/validators/attack_control_relationships.py
crml_lang/validators/common.py
crml_lang/validators/control_catalog.py
crml_lang/validators/control_relationships.py
crml_lang/validators/document.py
crml_lang/validators/portfolio.py
crml_lang/validators/portfolio_bundle.py
crml_lang/validators/scenario.py
crml_lang-1.2.1.dist-info/licenses/LICENSE
crml_lang-1.2.1.dist-info/METADATA
crml_lang-1.2.1.dist-info/WHEEL
crml_lang-1.2.1.dist-info/entry_points.txt
crml_lang-1.2.1.dist-info/top_level.txt
crml_lang-1.2.1.dist-info/RECORD
