Metadata-Version: 2.4
Name: crml-lang
Version: 1.2.1
Summary: CRML language/spec models, schema validator, and YAML IO
Author: Zeron Research Labs
Project-URL: Homepage, https://github.com/Faux16/crml
Project-URL: Repository, https://github.com/Faux16/crml
Project-URL: Documentation, https://faux16.github.io/crml/
Classifier: Programming Language :: Python :: 3
Classifier: License :: OSI Approved :: MIT License
Classifier: Operating System :: OS Independent
Requires-Python: >=3.9
License-File: LICENSE
Requires-Dist: pyyaml
Requires-Dist: jsonschema
Requires-Dist: pydantic
Provides-Extra: dev
Requires-Dist: pytest; extra == "dev"
Provides-Extra: xlsx
Requires-Dist: openpyxl>=3.1; extra == "xlsx"
Provides-Extra: oscal
Requires-Dist: compliance-trestle<4,>=3; extra == "oscal"
Dynamic: license-file
